[
  {
    "inputs": [],
    "stateMutability": "nonpayable",
    "type": "constructor"
  },
  {
    "anonymous": false,
    "inputs": [
      {
        "indexed": true,
        "internalType": "address",
        "name": "user",
        "type": "address"
      },
      {
        "indexed": true,
        "internalType": "string",
        "name": "symbol",
        "type": "string"
      },
      {
        "indexed": false,
        "internalType": "uint256",
        "name": "amount",
        "type": "uint256"
      }
    ],
    "name": "Borrow",
    "type": "event"
  },
  {
    "anonymous": false,
    "inputs": [
      {
        "indexed": true,
        "internalType": "address",
        "name": "user",
        "type": "address"
      },
      {
        "indexed": true,
        "internalType": "string",
        "name": "symbol",
        "type": "string"
      },
      {
        "indexed": false,
        "internalType": "uint256",
        "name": "amount",
        "type": "uint256"
      }
    ],
    "name": "Deposit",
    "type": "event"
  },
  {
    "anonymous": false,
    "inputs": [
      {
        "indexed": true,
        "internalType": "string",
        "name": "symbol",
        "type": "string"
      },
      {
        "indexed": false,
        "internalType": "uint256",
        "name": "oldRate",
        "type": "uint256"
      },
      {
        "indexed": false,
        "internalType": "uint256",
        "name": "newRate",
        "type": "uint256"
      }
    ],
    "name": "InterestRateUpdated",
    "type": "event"
  },
  {
    "anonymous": false,
    "inputs": [
      {
        "indexed": true,
        "internalType": "address",
        "name": "previousOwner",
        "type": "address"
      },
      {
        "indexed": true,
        "internalType": "address",
        "name": "newOwner",
        "type": "address"
      }
    ],
    "name": "OwnershipTransferred",
    "type": "event"
  },
  {
    "anonymous": false,
    "inputs": [
      {
        "indexed": true,
        "internalType": "address",
        "name": "user",
        "type": "address"
      },
      {
        "indexed": true,
        "internalType": "string",
        "name": "symbol",
        "type": "string"
      },
      {
        "indexed": false,
        "internalType": "uint256",
        "name": "amount",
        "type": "uint256"
      },
      {
        "indexed": false,
        "internalType": "uint256",
        "name": "interest",
        "type": "uint256"
      }
    ],
    "name": "Repay",
    "type": "event"
  },
  {
    "anonymous": false,
    "inputs": [
      {
        "indexed": true,
        "internalType": "address",
        "name": "user",
        "type": "address"
      },
      {
        "indexed": true,
        "internalType": "string",
        "name": "symbol",
        "type": "string"
      },
      {
        "indexed": false,
        "internalType": "uint256",
        "name": "amount",
        "type": "uint256"
      }
    ],
    "name": "Withdraw",
    "type": "event"
  },
  {
    "inputs": [
      {
        "internalType": "string",
        "name": "_symbol",
        "type": "string"
      },
      {
        "internalType": "address",
        "name": "_tokenAddress",
        "type": "address"
      },
      {
        "internalType": "address",
        "name": "_priceFeedAddress",
        "type": "address"
      },
      {
        "internalType": "uint256",
        "name": "_baseInterestRate",
        "type": "uint256"
      },
      {
        "internalType": "uint256",
        "name": "_collateralFactor",
        "type": "uint256"
      }
    ],
    "name": "addAsset",
    "outputs": [],
    "stateMutability": "nonpayable",
    "type": "function"
  },
  {
    "inputs": [
      {
        "internalType": "string",
        "name": "_symbol",
        "type": "string"
      },
      {
        "internalType": "uint256",
        "name": "_amount",
        "type": "uint256"
      }
    ],
    "name": "borrow",
    "outputs": [],
    "stateMutability": "nonpayable",
    "type": "function"
  },
  {
    "inputs": [
      {
        "internalType": "string",
        "name": "_symbol",
        "type": "string"
      },
      {
        "internalType": "uint256",
        "name": "_amount",
        "type": "uint256"
      }
    ],
    "name": "deposit",
    "outputs": [],
    "stateMutability": "nonpayable",
    "type": "function"
  },
  {
    "inputs": [],
    "name": "getAllAssetSymbols",
    "outputs": [
      {
        "internalType": "string[]",
        "name": "",
        "type": "string[]"
      }
    ],
    "stateMutability": "view",
    "type": "function"
  },
  {
    "inputs": [
      {
        "internalType": "string",
        "name": "_symbol",
        "type": "string"
      }
    ],
    "name": "getAssetDetails",
    "outputs": [
      {
        "internalType": "address",
        "name": "tokenAddress",
        "type": "address"
      },
      {
        "internalType": "uint256",
        "name": "totalDeposited",
        "type": "uint256"
      },
      {
        "internalType": "uint256",
        "name": "totalBorrowed",
        "type": "uint256"
      },
      {
        "internalType": "uint256",
        "name": "interestRate",
        "type": "uint256"
      },
      {
        "internalType": "uint256",
        "name": "collateralFactor",
        "type": "uint256"
      }
    ],
    "stateMutability": "view",
    "type": "function"
  },
  {
    "inputs": [
      {
        "internalType": "string",
        "name": "_symbol",
        "type": "string"
      }
    ],
    "name": "getAssetPrice",
    "outputs": [
      {
        "internalType": "uint256",
        "name": "",
        "type": "uint256"
      }
    ],
    "stateMutability": "view",
    "type": "function"
  },
  {
    "inputs": [
      {
        "internalType": "string",
        "name": "_symbol",
        "type": "string"
      }
    ],
    "name": "getCurrentInterestRate",
    "outputs": [
      {
        "internalType": "uint256",
        "name": "",
        "type": "uint256"
      }
    ],
    "stateMutability": "view",
    "type": "function"
  },
  {
    "inputs": [
      {
        "internalType": "address",
        "name": "_user",
        "type": "address"
      },
      {
        "internalType": "string",
        "name": "_symbol",
        "type": "string"
      }
    ],
    "name": "getUserPosition",
    "outputs": [
      {
        "internalType": "uint256",
        "name": "deposited",
        "type": "uint256"
      },
      {
        "internalType": "uint256",
        "name": "borrowed",
        "type": "uint256"
      },
      {
        "internalType": "uint256",
        "name": "interestDue",
        "type": "uint256"
      }
    ],
    "stateMutability": "view",
    "type": "function"
  },
  {
    "inputs": [],
    "name": "owner",
    "outputs": [
      {
        "internalType": "address",
        "name": "",
        "type": "address"
      }
    ],
    "stateMutability": "view",
    "type": "function"
  },
  {
    "inputs": [
      {
        "internalType": "string",
        "name": "_symbol",
        "type": "string"
      },
      {
        "internalType": "uint256",
        "name": "_amount",
        "type": "uint256"
      }
    ],
    "name": "repay",
    "outputs": [],
    "stateMutability": "nonpayable",
    "type": "function"
  },
  {
    "inputs": [
      {
        "internalType": "string",
        "name": "_symbol",
        "type": "string"
      },
      {
        "internalType": "uint256",
        "name": "_newRate",
        "type": "uint256"
      }
    ],
    "name": "updateInterestRate",
    "outputs": [],
    "stateMutability": "nonpayable",
    "type": "function"
  },
  {
    "inputs": [
      {
        "internalType": "string",
        "name": "_symbol",
        "type": "string"
      },
      {
        "internalType": "uint256",
        "name": "_amount",
        "type": "uint256"
      }
    ],
    "name": "withdraw",
    "outputs": [],
    "stateMutability": "nonpayable",
    "type": "function"
  }
]
